rpicammqtt_client/__init__.py
rpicammqtt_client/loadconfig.py
rpicammqtt_client/mqtt.py
rpicammqtt_client/config/rpi-cam-mqtt.yaml
rpicammqtt_client/data/rpicam_commands.yaml
rpicammqtt_client/examples/all_exposure_mode_pics.py
rpicammqtt_client/examples/all_image_effects.py
rpicammqtt_client/examples/monitor_status.py
rpicammqtt_client/examples/pantilt_view_switch.py
rpicammqtt_client/examples/rpicam_commands.py
rpicammqtt_client-0.3.0.dist-info/LICENSE
rpicammqtt_client-0.3.0.dist-info/METADATA
rpicammqtt_client-0.3.0.dist-info/WHEEL
rpicammqtt_client-0.3.0.dist-info/top_level.txt
rpicammqtt_client-0.3.0.dist-info/RECORD
