Metadata-Version: 2.1
Name: rpicammqtt-client
Version: 0.3.0
Summary: Client library to control a raspberry PI camera through MQTT
Home-page: https://gitlab.com/gbus/rpi-cam-mqtt-client
Author: Gianluca Busiello
Author-email: gianluca.busiello@gmail.com
License: UNKNOWN
Platform: UNKNOWN
Classifier: Programming Language :: Python :: 3
Classifier: License :: OSI Approved :: Apache Software License
Classifier: Operating System :: POSIX :: Linux
Requires-Dist: PyYaml (>=3.12)
Requires-Dist: paho-mqtt (>=1.4.0)
